{
  "proyectos": [
    {
      "altaObaja": "ACTIVO",
      "administrador": {
        "estado": "ACTIVO",
        "password": 1234,
        "lideresACargo": [],
        "apellido": "Richiardi",
        "titulo": "Computer Science",
        "id": 73488,
        "nombre": "Monica",
        "email": "moni@hotmail.com"
      },
      "estado": "PENDIENTE",
      "lider": {
        "estado": "ACTIVO",
        "password": 1234,
        "miembrosACargo": [],
        "apellido": "Wazowszki",
        "titulo": "Asustador",
        "id": 13253,
        "nombre": "Mike",
        "email": "Mikewazawski@gmail.com",
        "proyectosEnCurso": []
      },
      "equipo": [
        {
          "estado": "ACTIVO",
          "password": 1234,
          "apellido": "Fernandez",
          "titulo": "Futbolista",
          "id": 30519,
          "nombre": "Enzo",
          "email": "elmaleducado21@gmail.com",
          "rol": "DEVOPS",
          "proyectosEnCurso": []
        },
        {
          "estado": "ACTIVO",
          "password": 1234,
          "apellido": "Messi",
          "titulo": "Futbolista",
          "id": 52035,
          "nombre": "Lionel",
          "email": "lapulga10@gmail.com",
          "rol": "DEVOPS",
          "proyectosEnCurso": []
        },
        {
          "estado": "ACTIVO",
          "password": 1234,
          "apellido": "Aguero",
          "titulo": "Streamer",
          "id": 53015,
          "nombre": "Sergio",
          "email": "kunaguero@gmail.com",
          "rol": "DEVOPS",
          "proyectosEnCurso": []
        },
        {
          "estado": "ACTIVO",
          "password": 1234,
          "apellido": "DiMaria",
          "titulo": "Futbolista",
          "id": 28673,
          "nombre": "Angel",
          "email": "fideo11@gmail.com",
          "rol": "DEVOPS",
          "proyectosEnCurso": []
        },
        {
          "estado": "ACTIVO",
          "password": 1234,
          "apellido": "Martinez",
          "titulo": "Arquero",
          "id": 53469,
          "nombre": "Emiliano",
          "email": "dibu1@gmail.com",
          "rol": "DEVOPS",
          "proyectosEnCurso": []
        }
      ],
      "id": 90750,
      "tareas": [
        {
          "descripcion": "Creamos e instanciamos las clases. Primer commit",
          "altaObaja": "ACTIVO",
          "estado": "PENDIENTE",
          "responsable": {
            "estado": "ACTIVO",
            "password": 1234,
            "apellido": "Fernandez",
            "titulo": "Futbolista",
            "id": 30519,
            "nombre": "Enzo",
            "email": "elmaleducado21@gmail.com",
            "rol": "DEVOPS",
            "proyectosEnCurso": []
          },
          "titulo": "Sprint 1",
          "id": 70315
        },
        {
          "descripcion": "Instanciar clases. Segundo commit",
          "altaObaja": "ACTIVO",
          "estado": "PENDIENTE",
          "responsable": {
            "estado": "ACTIVO",
            "password": 1234,
            "apellido": "Messi",
            "titulo": "Futbolista",
            "id": 52035,
            "nombre": "Lionel",
            "email": "lapulga10@gmail.com",
            "rol": "DEVOPS",
            "proyectosEnCurso": []
          },
          "titulo": "Sprint 2",
          "id": 71745
        },
        {
          "descripcion": "Primer prueba",
          "altaObaja": "ACTIVO",
          "estado": "PENDIENTE",
          "responsable": {
            "estado": "ACTIVO",
            "password": 1234,
            "apellido": "DiMaria",
            "titulo": "Futbolista",
            "id": 28673,
            "nombre": "Angel",
            "email": "fideo11@gmail.com",
            "rol": "DEVOPS",
            "proyectosEnCurso": []
          },
          "titulo": "Sprint 3",
          "id": 33408
        },
        {
          "descripcion": "Implementamos los métodos principales y realizamos pruebas iniciales",
          "altaObaja": "ACTIVO",
          "estado": "PENDIENTE",
          "responsable": {
            "estado": "ACTIVO",
            "password": 1234,
            "apellido": "Aguero",
            "titulo": "Streamer",
            "id": 53015,
            "nombre": "Sergio",
            "email": "kunaguero@gmail.com",
            "rol": "DEVOPS",
            "proyectosEnCurso": []
          },
          "titulo": "Sprint 2",
          "id": 39534
        },
        {
          "descripcion": "Optimizamos el código y documentamos el proyecto",
          "altaObaja": "ACTIVO",
          "estado": "PENDIENTE",
          "responsable": {
            "estado": "ACTIVO",
            "password": 1234,
            "apellido": "Martinez",
            "titulo": "Arquero",
            "id": 53469,
            "nombre": "Emiliano",
            "email": "dibu1@gmail.com",
            "rol": "DEVOPS",
            "proyectosEnCurso": []
          },
          "titulo": "Sprint 3",
          "id": 34786
        }
      ],
      "nombre": "TPFINAL"
    },
    {
      "altaObaja": "ACTIVO",
      "administrador": {
        "estado": "ACTIVO",
        "password": 1234,
        "lideresACargo": [],
        "apellido": "II",
        "titulo": "Emperador",
        "id": 39940,
        "nombre": "Cesar",
        "email": "ceseremperador@hotmail.com"
      },
      "estado": "PENDIENTE",
      "lider": {
        "estado": "ACTIVO",
        "password": 1234,
        "miembrosACargo": [],
        "apellido": "Mikelson",
        "titulo": "Asustador",
        "id": 4487,
        "nombre": "Sullivan",
        "email": "sullivan@gmail.com",
        "proyectosEnCurso": []
      },
      "equipo": [
        {
          "estado": "ACTIVO",
          "password": 1234,
          "apellido": "Fernandez",
          "titulo": "Futbolista",
          "id": 30519,
          "nombre": "Enzo",
          "email": "elmaleducado21@gmail.com",
          "rol": "DEVOPS",
          "proyectosEnCurso": []
        },
        {
          "estado": "ACTIVO",
          "password": 1234,
          "apellido": "Messi",
          "titulo": "Futbolista",
          "id": 52035,
          "nombre": "Lionel",
          "email": "lapulga10@gmail.com",
          "rol": "DEVOPS",
          "proyectosEnCurso": []
        },
        {
          "estado": "ACTIVO",
          "password": 1234,
          "apellido": "Aguero",
          "titulo": "Streamer",
          "id": 53015,
          "nombre": "Sergio",
          "email": "kunaguero@gmail.com",
          "rol": "DEVOPS",
          "proyectosEnCurso": []
        },
        {
          "estado": "ACTIVO",
          "password": 1234,
          "apellido": "DiMaria",
          "titulo": "Futbolista",
          "id": 28673,
          "nombre": "Angel",
          "email": "fideo11@gmail.com",
          "rol": "DEVOPS",
          "proyectosEnCurso": []
        }
      ],
      "id": 63416,
      "tareas": [
        {
          "descripcion": "Creamos e instanciamos las clases. Primer commit",
          "altaObaja": "ACTIVO",
          "estado": "PENDIENTE",
          "responsable": {
            "estado": "ACTIVO",
            "password": 1234,
            "apellido": "Fernandez",
            "titulo": "Futbolista",
            "id": 30519,
            "nombre": "Enzo",
            "email": "elmaleducado21@gmail.com",
            "rol": "DEVOPS",
            "proyectosEnCurso": []
          },
          "titulo": "Sprint 1",
          "id": 70315
        },
        {
          "descripcion": "Instanciar clases. Segundo commit",
          "altaObaja": "ACTIVO",
          "estado": "PENDIENTE",
          "responsable": {
            "estado": "ACTIVO",
            "password": 1234,
            "apellido": "Messi",
            "titulo": "Futbolista",
            "id": 52035,
            "nombre": "Lionel",
            "email": "lapulga10@gmail.com",
            "rol": "DEVOPS",
            "proyectosEnCurso": []
          },
          "titulo": "Sprint 2",
          "id": 71745
        },
        {
          "descripcion": "Primer prueba",
          "altaObaja": "ACTIVO",
          "estado": "PENDIENTE",
          "responsable": {
            "estado": "ACTIVO",
            "password": 1234,
            "apellido": "DiMaria",
            "titulo": "Futbolista",
            "id": 28673,
            "nombre": "Angel",
            "email": "fideo11@gmail.com",
            "rol": "DEVOPS",
            "proyectosEnCurso": []
          },
          "titulo": "Sprint 3",
          "id": 33408
        },
        {
          "descripcion": "Implementamos los métodos principales y realizamos pruebas iniciales",
          "altaObaja": "ACTIVO",
          "estado": "PENDIENTE",
          "responsable": {
            "estado": "ACTIVO",
            "password": 1234,
            "apellido": "Aguero",
            "titulo": "Streamer",
            "id": 53015,
            "nombre": "Sergio",
            "email": "kunaguero@gmail.com",
            "rol": "DEVOPS",
            "proyectosEnCurso": []
          },
          "titulo": "Sprint 2",
          "id": 39534
        }
      ],
      "nombre": "Aplicación Web"
    },
    {
      "altaObaja": "ACTIVO",
      "administrador": {
        "estado": "ACTIVO",
        "password": 1234,
        "lideresACargo": [],
        "apellido": "González",
        "titulo": "Information Systems",
        "id": 25419,
        "nombre": "Lucas",
        "email": "lucas.gonzalez@example.com"
      },
      "estado": "PENDIENTE",
      "lider": {
        "estado": "ACTIVO",
        "password": 1234,
        "miembrosACargo": [],
        "apellido": "Boggs",
        "titulo": "Asustador Experto",
        "id": 94033,
        "nombre": "Randall",
        "email": "randall.boggs@gmail.com",
        "proyectosEnCurso": []
      },
      "equipo": [
        {
          "estado": "ACTIVO",
          "password": 1234,
          "apellido": "Fernandez",
          "titulo": "Futbolista",
          "id": 30519,
          "nombre": "Enzo",
          "email": "elmaleducado21@gmail.com",
          "rol": "DEVOPS",
          "proyectosEnCurso": []
        },
        {
          "estado": "ACTIVO",
          "password": 1234,
          "apellido": "Messi",
          "titulo": "Futbolista",
          "id": 52035,
          "nombre": "Lionel",
          "email": "lapulga10@gmail.com",
          "rol": "DEVOPS",
          "proyectosEnCurso": []
        },
        {
          "estado": "ACTIVO",
          "password": 1234,
          "apellido": "Aguero",
          "titulo": "Streamer",
          "id": 53015,
          "nombre": "Sergio",
          "email": "kunaguero@gmail.com",
          "rol": "DEVOPS",
          "proyectosEnCurso": []
        }
      ],
      "id": 4791,
      "tareas": [
        {
          "descripcion": "Creamos e instanciamos las clases. Primer commit",
          "altaObaja": "ACTIVO",
          "estado": "PENDIENTE",
          "responsable": {
            "estado": "ACTIVO",
            "password": 1234,
            "apellido": "Fernandez",
            "titulo": "Futbolista",
            "id": 30519,
            "nombre": "Enzo",
            "email": "elmaleducado21@gmail.com",
            "rol": "DEVOPS",
            "proyectosEnCurso": []
          },
          "titulo": "Sprint 1",
          "id": 70315
        },
        {
          "descripcion": "Instanciar clases. Segundo commit",
          "altaObaja": "ACTIVO",
          "estado": "PENDIENTE",
          "responsable": {
            "estado": "ACTIVO",
            "password": 1234,
            "apellido": "Messi",
            "titulo": "Futbolista",
            "id": 52035,
            "nombre": "Lionel",
            "email": "lapulga10@gmail.com",
            "rol": "DEVOPS",
            "proyectosEnCurso": []
          },
          "titulo": "Sprint 2",
          "id": 71745
        },
        {
          "descripcion": "Primer prueba",
          "altaObaja": "ACTIVO",
          "estado": "PENDIENTE",
          "responsable": {
            "estado": "ACTIVO",
            "password": 1234,
            "apellido": "DiMaria",
            "titulo": "Futbolista",
            "id": 28673,
            "nombre": "Angel",
            "email": "fideo11@gmail.com",
            "rol": "DEVOPS",
            "proyectosEnCurso": []
          },
          "titulo": "Sprint 3",
          "id": 33408
        }
      ],
      "nombre": "Diseño de la DB"
    },
    {
      "altaObaja": "ACTIVO",
      "administrador": {
        "estado": "ACTIVO",
        "password": 1234,
        "lideresACargo": [],
        "apellido": "Ramírez",
        "titulo": "Software Engineering",
        "id": 71390,
        "nombre": "Carla",
        "email": "carla.ramirez@example.com"
      },
      "estado": "PENDIENTE",
      "lider": {
        "estado": "ACTIVO",
        "password": 1234,
        "miembrosACargo": [],
        "apellido": "Doe",
        "titulo": "Supervisora",
        "id": 74260,
        "nombre": "Roz",
        "email": "roz.doe@gmail.com",
        "proyectosEnCurso": []
      },
      "equipo": [
        {
          "estado": "ACTIVO",
          "password": 1234,
          "apellido": "Fernandez",
          "titulo": "Futbolista",
          "id": 30519,
          "nombre": "Enzo",
          "email": "elmaleducado21@gmail.com",
          "rol": "DEVOPS",
          "proyectosEnCurso": []
        },
        {
          "estado": "ACTIVO",
          "password": 1234,
          "apellido": "Messi",
          "titulo": "Futbolista",
          "id": 52035,
          "nombre": "Lionel",
          "email": "lapulga10@gmail.com",
          "rol": "DEVOPS",
          "proyectosEnCurso": []
        }
      ],
      "id": 9859,
      "tareas": [
        {
          "descripcion": "Creamos e instanciamos las clases. Primer commit",
          "altaObaja": "ACTIVO",
          "estado": "PENDIENTE",
          "responsable": {
            "estado": "ACTIVO",
            "password": 1234,
            "apellido": "Fernandez",
            "titulo": "Futbolista",
            "id": 30519,
            "nombre": "Enzo",
            "email": "elmaleducado21@gmail.com",
            "rol": "DEVOPS",
            "proyectosEnCurso": []
          },
          "titulo": "Sprint 1",
          "id": 70315
        },
        {
          "descripcion": "Instanciar clases. Segundo commit",
          "altaObaja": "ACTIVO",
          "estado": "PENDIENTE",
          "responsable": {
            "estado": "ACTIVO",
            "password": 1234,
            "apellido": "Messi",
            "titulo": "Futbolista",
            "id": 52035,
            "nombre": "Lionel",
            "email": "lapulga10@gmail.com",
            "rol": "DEVOPS",
            "proyectosEnCurso": []
          },
          "titulo": "Sprint 2",
          "id": 71745
        }
      ],
      "nombre": "Rediseño de la pagina principal"
    },
    {
      "altaObaja": "ACTIVO",
      "administrador": {
        "estado": "ACTIVO",
        "password": 1234,
        "lideresACargo": [],
        "apellido": "Fernández",
        "titulo": "Data Science",
        "id": 14268,
        "nombre": "Diego",
        "email": "diego.fernandez@example.com"
      },
      "estado": "PENDIENTE",
      "lider": {
        "estado": "ACTIVO",
        "password": 1234,
        "miembrosACargo": [],
        "apellido": "Mae",
        "titulo": "Recepcionista",
        "id": 47153,
        "nombre": "Celia",
        "email": "celia.mae@gmail.com",
        "proyectosEnCurso": []
      },
      "equipo": [
        {
          "estado": "ACTIVO",
          "password": 1234,
          "apellido": "Fernandez",
          "titulo": "Futbolista",
          "id": 30519,
          "nombre": "Enzo",
          "email": "elmaleducado21@gmail.com",
          "rol": "DEVOPS",
          "proyectosEnCurso": []
        }
      ],
      "id": 57613,
      "tareas": [
        {
          "descripcion": "Creamos e instanciamos las clases. Primer commit",
          "altaObaja": "ACTIVO",
          "estado": "PENDIENTE",
          "responsable": {
            "estado": "ACTIVO",
            "password": 1234,
            "apellido": "Fernandez",
            "titulo": "Futbolista",
            "id": 30519,
            "nombre": "Enzo",
            "email": "elmaleducado21@gmail.com",
            "rol": "DEVOPS",
            "proyectosEnCurso": []
          },
          "titulo": "Sprint 1",
          "id": 70315
        }
      ],
      "nombre": "Otro Proyecto"
    }
  ]
}